konva_report/__init__.py
konva_report/konva_report.py
konva_report-0.11.dist-info/METADATA
konva_report-0.11.dist-info/WHEEL
konva_report-0.11.dist-info/top_level.txt
konva_report-0.11.dist-info/RECORD
