Metadata-Version: 2.1
Name: konva-report
Version: 0.11
Summary: konva_report
Home-page: UNKNOWN
Author: Cesar Cañas
Author-email: cdcanasg@gmail.com
License: UNKNOWN
Platform: UNKNOWN
Classifier: Programming Language :: Python :: 3
Classifier: License :: OSI Approved :: MIT License
Classifier: Operating System :: OS Independent
Requires-Dist: reportlab
